{"skin":"night","craft":["{\"Title\":\"rere\",\"Finished\":\"25-11-2018 04:48:34\"}","{\"Title\":\"ssdfsf\",\"Finished\":\"25-11-2018 04:48:34\"}","{\"Title\":\"retro\",\"Finished\":\"25-11-2018 04:48:34\"}","{\"Title\":\"nouveau\",\"Finished\":\"02/12/2018 01:26:47\"}","{\"Title\":\"encore\",\"Finished\":\"09/12/2018 01:35:37\"}","{\"Title\":\"un autre\",\"Finished\":\"12/12/2018 20:39:26\"}","{\"Title\":\"tomtom\",\"Finished\":\"11/12/2018 11:39:53\"}","{\"Title\":\"derniere ligne\",\"Finished\":\"11/12/2018 02:06:05\"}","{\"Title\":\"azezeaz\",\"Finished\":\"15/12/2018 14:51:21\"}","{\"Title\":\"efqds\",\"Finished\":\"14/12/2018 14:51:29\"}","{\"Title\":\"lolo\",\"Finished\":\"15/12/2018 14:51:39\"}","{\"Title\":\"mpmpmp\",\"Finished\":\"15/12/2018 03:51:48\"}","{\"Title\":\"autre ligne\",\"Finished\":\"15/12/2018 00:53:08\"}"]}